Motor_imagery_ge/__init__.py
Motor_imagery_ge/evaluate.py
Motor_imagery_ge/main.py
Motor_imagery_ge-1.0.dist-info/METADATA
Motor_imagery_ge-1.0.dist-info/WHEEL
Motor_imagery_ge-1.0.dist-info/top_level.txt
Motor_imagery_ge-1.0.dist-info/RECORD
