Metadata-Version: 2.1
Name: Motor-imagery-ge
Version: 1.0
Summary: 4 classes Motor Imagery EEG data classification.
Author: Grigorakou Eftychia
